aoikpymopa/aoikpmp.py
aoikpymopa/__init__.py
aoikpymopa/__main__.py
AoikPyMoPa-0.1.0.dist-info/DESCRIPTION.rst
AoikPyMoPa-0.1.0.dist-info/entry_points.txt
AoikPyMoPa-0.1.0.dist-info/METADATA
AoikPyMoPa-0.1.0.dist-info/metadata.json
AoikPyMoPa-0.1.0.dist-info/RECORD
AoikPyMoPa-0.1.0.dist-info/top_level.txt
AoikPyMoPa-0.1.0.dist-info/WHEEL
