Metadata-Version: 2.0
Name: AoikPyMoPa
Version: 0.1.0
Summary: Find a Python module's file paths. Have considered Implicit Namespace Packages introduced in PEP 420. Handy for debugging tricky importing problems.
Home-page: https://github.com/AoiKuiyuyou/AoikPyMoPa
Author: Aoi.Kuiyuyou
Author-email: aoi.kuiyuyou@google.com
License: MIT
Keywords: Find Python module file path
Platform: UNKNOWN
Classifier: Development Status :: 3 - Alpha
Classifier: Environment :: Console
Classifier: Intended Audience :: Developers
Classifier: License :: OSI Approved :: MIT License
Classifier: Programming Language :: Python :: 2
Classifier: Programming Language :: Python :: 2.3
Classifier: Programming Language :: Python :: 2.4
Classifier: Programming Language :: Python :: 2.5
Classifier: Programming Language :: Python :: 2.6
Classifier: Programming Language :: Python :: 2.7
Classifier: Programming Language :: Python :: 3
Classifier: Programming Language :: Python :: 3.0
Classifier: Programming Language :: Python :: 3.1
Classifier: Programming Language :: Python :: 3.2
Classifier: Programming Language :: Python :: 3.3
Classifier: Programming Language :: Python :: 3.4
